{
  "date": "2026-04-30",
  "timestamp": "2026-04-30T15:00:00+08:00",
  "data_source": "Sina Finance API",
  "note": "北向资金和行业板块明细因EastMoney/东方财富API超时未获取到",
  "indices": [
    {
      "name": "上证指数",
      "price": 4112.16,
      "change_pct": 0.11,
      "change_amount": 4.64,
      "open": 4107.30,
      "prev_close": 4107.51,
      "high": 4112.16,
      "low": 4104.57,
      "volume": 6569127
    },
    {
      "name": "深证成指",
      "price": 15107.55,
      "change_pct": -0.09,
      "change_amount": -13.37,
      "open": 15111.33,
      "prev_close": 15120.92,
      "high": null,
      "low": null,
      "volume": 737703742
    },
    {
      "name": "创业板指",
      "price": 3677.15,
      "change_pct": -0.27,
      "change_amount": -10.02,
      "open": 3682.49,
      "prev_close": 3687.17,
      "high": null,
      "low": null,
      "volume": 35458459
    },
    {
      "name": "沪深300",
      "price": 4807.31,
      "change_pct": -0.06,
      "change_amount": -3.04,
      "open": 4809.76,
      "prev_close": 4810.35,
      "high": null,
      "low": null,
      "volume": 2506333
    }
  ],
  "sectors": {
    "summary": "AI应用、机器人、算力、消费电子、华为鸿蒙、半导体、低空经济概念股活跃；银行股全线调整，电力、港口板块跌幅靠前",
    "top5": [],
    "bottom5": []
  },
  "north_flow": {
    "value": null,
    "note": "数据获取失败（EastMoney API超时）"
  }
}
