{
  "date": "2026-06-17",
  "updated_at": "2026-06-17 15:16:36",
  "indices": {
    "上证指数": {
      "code": "000001",
      "price": "4108.08",
      "change_pct": 0.4,
      "change": 16.18
    },
    "深证成指": {
      "code": "399001",
      "price": "15880.95",
      "change_pct": 1.31,
      "change": 205.71
    },
    "创业板指": {
      "code": "399006",
      "price": "4167.05",
      "change_pct": 1.56,
      "change": 64.11
    },
    "沪深300": {
      "code": "000300",
      "price": "4931.39",
      "change_pct": 0.97,
      "change": 47.15
    },
    "科创50": {
      "code": "000688",
      "price": "1840.82",
      "change_pct": 4.69,
      "change": 82.4
    }
  },
  "indices_summary": "科创50大涨4.69%领跑，创业板指涨1.56%，市场整体偏暖。",
  "sectors": {
    "description": "数据来源东财行业板块（实时拉取失败，使用搜索摘要）",
    "top_gainers": [],
    "top_losers": [],
    "key_sectors": {}
  },
  "northbound_flow": {
    "description": "北向资金日度数据未获取到（API不可达）"
  },
  "market_summary": "三大指数全线上涨，科创50大涨4.69%表现亮眼，半导体等科技板块走强。",
  "data_source": "sina_finance_api"
}